tap_partnerize/__init__.py
tap_partnerize/client.py
tap_partnerize/streams.py
tap_partnerize/tap.py
tap_partnerize-0.0.4.dist-info/LICENSE
tap_partnerize-0.0.4.dist-info/METADATA
tap_partnerize-0.0.4.dist-info/WHEEL
tap_partnerize-0.0.4.dist-info/entry_points.txt
tap_partnerize-0.0.4.dist-info/RECORD
